<?xml version="1.0"?>
<SOAP-ENV:Envelope xmlns:SOAP-ENV="http://schemas.xmlsoap.org/soap/envelope/"><SOAP-ENV:Header><SOAP-SEC:Signature xmlns:SOAP-SEC="http://schemas.xmlsoap.org/soap/security/2000-12" SOAP-ENV:actor="some-URI" SOAP-ENV:mustUnderstand="1"><ds:Signature xmlns:ds="http://www.w3.org/2000/09/xmldsig#"><ds:SignedInfo><ds:CanonicalizationMethod Algorithm="http://www.w3.org/TR/2000/CR-xml-c14n-20001026"></ds:CanonicalizationMethod><ds:SignatureMethod Algorithm="http://www.w3.org/2000/09/xmldsig#dsa-sha1"/><ds:Reference URI="#Body"><ds:Transforms><ds:Transform Algorithm="http://www.w3.org/TR/2000/CR-xml-c14n-20001026"/></ds:Transforms><ds:DigestMethod Algorithm="http://www.w3.org/2000/09/xmldsig#sha1"/><ds:DigestValue>j6lwx3rvEPO0vKtMup4NbeVu8nk=</ds:DigestValue></ds:Reference></ds:SignedInfo><ds:SignatureValue>MC0CFFrVLtRlk=...</ds:SignatureValue></ds:Signature></SOAP-SEC:Signature></SOAP-ENV:Header><SOAP-ENV:Body xmlns:SOAP-SEC="http://schemas.xmlsoap.org/soap/security/2000-12" SOAP-SEC:id="Body"><m:GetLastTradePrice xmlns:m="some-URI"><m:symbol>IBM</m:symbol></m:GetLastTradePrice></SOAP-ENV:Body></SOAP-ENV:Envelope>
